systemonachip/__init__.py
systemonachip/bus/__init__.py
systemonachip/bus/decoder.py
systemonachip/cpu/__init__.py
systemonachip/cpu/minerva.py
systemonachip/event/__init__.py
systemonachip/peripheral/__init__.py
systemonachip/peripheral/base.py
systemonachip/peripheral/event.py
systemonachip/peripheral/interrupt.py
systemonachip/peripheral/memory.py
systemonachip/peripheral/serial.py
systemonachip/peripheral/timer.py
systemonachip/register/__init__.py
systemonachip/register/readwrite.py
systemonachip/register/static.py
systemonachip/soc/__init__.py
systemonachip/soc/base.py
systemonachip/soc/cpu.py
systemonachip/software/__init__.py
systemonachip/test/_wishbone.py
systemonachip/test/test_periph_base.py
systemonachip/test/test_periph_event.py
systemonachip/test/test_periph_intc.py
systemonachip/test/test_periph_serial.py
systemonachip/test/test_periph_sram.py
systemonachip/test/test_periph_timer.py
systemonachip-0.0.1.dist-info/LICENSE.txt
systemonachip-0.0.1.dist-info/METADATA
systemonachip-0.0.1.dist-info/WHEEL
systemonachip-0.0.1.dist-info/top_level.txt
systemonachip-0.0.1.dist-info/RECORD
